python_usps2-0.2.0.dist-info/DESCRIPTION.rst
python_usps2-0.2.0.dist-info/METADATA
python_usps2-0.2.0.dist-info/metadata.json
python_usps2-0.2.0.dist-info/RECORD
python_usps2-0.2.0.dist-info/top_level.txt
python_usps2-0.2.0.dist-info/WHEEL
usps/__init__.py
usps/addressinformation/__init__.py
usps/addressinformation/base.py
